qdprint.py
qdprint-0.1.1.dist-info/METADATA
qdprint-0.1.1.dist-info/WHEEL
qdprint-0.1.1.dist-info/entry_points.txt
qdprint-0.1.1.dist-info/top_level.txt
qdprint-0.1.1.dist-info/RECORD
