Metadata-Version: 2.4
Name: qdPrint
Version: 0.1.1
Summary: A simple library for colored printing in Python
Requires-Python: >=3.6
